multick/__init__.py
multick-0.0.0.dist-info/WHEEL
multick-0.0.0.dist-info/METADATA
multick-0.0.0.dist-info/RECORD
