Metadata-Version: 2.3
Name: multick
Version: 0.0.0
Summary: An application to view a stocker ticker across multiple timeframes.
Requires-Python: >=3.13
